shadowkv/__init__.py
shadowkv/example.py
shadowkv-0.0.0.dist-info/METADATA
shadowkv-0.0.0.dist-info/WHEEL
shadowkv-0.0.0.dist-info/licenses/LICENSE
shadowkv-0.0.0.dist-info/RECORD
